grmaster-0.1.3.dist-info/top_level.txt
grmaster-0.1.3.dist-info/RECORD
grmaster-0.1.3.dist-info/metadata.json
grmaster-0.1.3.dist-info/entry_points.txt
grmaster-0.1.3.dist-info/DESCRIPTION.rst
grmaster-0.1.3.dist-info/WHEEL
grmaster-0.1.3.dist-info/METADATA
grmaster/__main__.py
grmaster/rules.py
grmaster/server.py
grmaster/setting.py
grmaster/table.py
grmaster/manager.py
grmaster/__init__.py
grmaster/data/template.csv
grmaster/data/index.en.html
grmaster/data/students.csv
grmaster/data/index.ru.html
grmaster/data/LICENSE.txt
grmaster/data/__init__.py
grmaster/data/tests/test_data.py
grmaster/data/tests/__init__.py
grmaster/tests/test_manager.py
grmaster/tests/test_table.py
grmaster/tests/test_server.py
grmaster/tests/test_rules.py
grmaster/tests/test_main.py
grmaster/tests/__init__.py
