Metadata-Version: 2.0
Name: grmaster
Version: 0.1.3
Summary: Tool for dividing students into groups.
Home-page: https://github.com/vslutov/grmaster
Author: vslutov
Author-email: vslutov@yandex.ru
License: https://gnu.org/licenses/agpl.html
Platform: any
Classifier: Development Status :: 3 - Alpha
Classifier: Environment :: Console
Classifier: Environment :: Web Environment
Classifier: Intended Audience :: Education
Classifier: License :: OSI Approved :: GNU Affero General Public License v3 or later (AGPLv3+)
Classifier: Natural Language :: Russian
Classifier: Natural Language :: English
Classifier: Operating System :: Unix
Classifier: Operating System :: Microsoft :: Windows
Classifier: Programming Language :: Python :: 3 :: Only
Classifier: Topic :: Database
Classifier: Topic :: Education
Classifier: Topic :: Sociology
Classifier: Topic :: Utilities
Requires-Dist: flask
Requires-Dist: pytest
